manna.py
manna-1.1.dist-info/METADATA
manna-1.1.dist-info/WHEEL
manna-1.1.dist-info/top_level.txt
manna-1.1.dist-info/RECORD
