Metadata-Version: 2.1
Name: manna
Version: 1.1
Summary: stegocrypter
Author: Neelanjan Manna
Classifier: Programming Language :: Python :: 3
Classifier: License :: OSI Approved :: MIT License
Classifier: Operating System :: OS Independent
Requires-Python: >=2.0
Requires-Dist: pycryptodome
